cdklabs/aws_lambda_dotnet/__init__.py
cdklabs/aws_lambda_dotnet/py.typed
cdklabs/aws_lambda_dotnet/_jsii/__init__.py
cdklabs/aws_lambda_dotnet/_jsii/aws-lambda-dotnet@0.0.0.jsii.tgz
cdklabs.aws_lambda_dotnet-0.0.0.dist-info/LICENSE
cdklabs.aws_lambda_dotnet-0.0.0.dist-info/METADATA
cdklabs.aws_lambda_dotnet-0.0.0.dist-info/WHEEL
cdklabs.aws_lambda_dotnet-0.0.0.dist-info/top_level.txt
cdklabs.aws_lambda_dotnet-0.0.0.dist-info/RECORD
